Workbook

Sheet START HERE
A2: 🏠 Heartland Restoration Budget Model
A3: Version 1.2 • Built for easy use — anyone can drive this
A5: This workbook tells you ONE thing: are you going to make money this month, and what does it take to keep making money? You enter your costs and what you charge. The math happens for you.
A8: 🆕 What's new in v1.2
B10: • LABOR TAB — Clearer columns. You now see paid hours and billable hours side-by-side. The old 'Util %' is now 'Billable Time %' — what % of paid time you can invoice. Hover over any column header for an in-cell explanation. • EQUIPMENT TAB — One simpler input. Instead of asking 'days deployed per unit', the model now asks for total UNIT-DAYS RENTED in a month — the actual rental volume. Plus a new 'Fleet Utilization %' column shows you which gear is sitting idle.
A12: 🎨 COLOR GUIDE — How to read this workbook
B14: Yellow box, blue text | C14: YOU CHANGE THIS | D14: These are your inputs. Change anything yellow.
B15: Black text | C15: DON'T TOUCH | D15: These are formulas. They calculate automatically.
B16: Green text | C16: PULLED FROM ANOTHER TAB | D16: These pull numbers from a different sheet.
B17: Light green box | C17: WORKED EXAMPLE | D17: Walk-through example showing how the math works.
B18: Peach fill | C18: TOTAL or RESULT | D18: Subtotals and final answers live here.
B19: Light blue fill | C19: SECTION HEADER | D19: Just a label dividing parts of a tab.
B20: Green = profit, Red = loss | C20: RESULT INDICATOR | D20: On the Dashboard, green means you made money.
A23: 📋 TABS — Walk through them in this order
B25: 1. Overhead | C25: Your monthly fixed bills (rent, insurance, software, owner draw, etc.)
B26: 2. Labor | C26: Tech roster — one row per person. Each has their own wage.
B27: 3. Equipment | C27: Air movers, dehus, etc. — what each unit makes you per month.
B28: 4. Investments | C28: Vehicles, offices, big buys. Add a row, see the impact.
B29: 5. Packaged Items | C29: Decon chambers and other fixed-price kits — what they really cost.
B30: 6. DASHBOARD | C30: 👉 Your answers live here. Profit, break-even, sensitivity table.
A33: 🚦 HOW TO USE IT — 4 steps
B35: 1. Go through tabs 1–5 in order. Fill in every yellow box you can. Skip the rest for now.
B36: 2. Each input-heavy tab has a green WORKED EXAMPLE box — read it first if you're unsure.
B37: 3. Open the DASHBOARD tab. Read your monthly profit/loss and break-even.
B38: 4. Try changes. Add a vehicle on the Investments tab. Watch the dashboard recalc.

Sheet 1. Overhead
A2: 1. Monthly Overhead — your fixed bills
A3: These are bills you pay every month no matter what — even if you don't do a single job. Yellow = change it. Add your own categories at the bottom. Owner draw is included so the model treats your $5,000 take-home as a real cost.
B5: Category | C5: Monthly Cost | D5: Notes
B6: Office / shop rent | C6: 0 | D6: Your physical location
B7: Property / liability insurance | C7: 375 | D7: GL, property, umbrella
B8: Workers comp insurance | C8: 0 | D8: If billed monthly (otherwise leave 0 — it's loaded into Labor tab)
B9: Software (CRM, accounting, etc.) | C9: 869 | D9: QuickBooks, ServiceReady, dispatch software, etc.
B10: Phones & internet | C10: 322 | D10: Office + tech cell phones
B11: Marketing & advertising | C11: 5000 | D11: PPC, LSA, SEO, print, GMB tools
B12: Office utilities | C12: 150 | D12: Power, water, gas, trash
B13: Accounting / bookkeeping | C13: 1500 | D13: CPA, bookkeeper retainer
B14: Legal / professional fees | C14: 200 | D14: Avg monthly amortized
B15: Office supplies | C15: 100 | D15: Paper, printer, small stuff
B16: Bank / merchant fees | C16: 0 | D16: Card processing, bank charges
B17: Subscriptions & memberships | C17: 0 | D17: IICRC, RIA, trade groups
... B19: Debt service (loans not on Investments tab) | C19: 3800 | D19: Existing LOC, term loans
B20: Training & certifications | C20: 0
B21: Other 1 | C21: 460 | D21: Add anything
B22: Other 2 | C22: 0 | D22: Add anything
B23: Other 3 | C23: 0 | D23: Add anything
B24: Other 4 | C24: 0 | D24: Add anything
B25: Other 5 | C25: 0 | D25: Add anything
B26: TOTAL MONTHLY OVERHEAD | C26: =SUM(C6:C25) -> 17776

Sheet 2. Labor
A2: 2. Labor — tech roster (per-tech wages)
A3: Each row is one tech. Enter their wage, hours per week, and any benefits. The yellow cells are inputs. The model calculates each person's fully-loaded cost and cost per billable hour — and a weighted team average that other tabs use. Tip: hover over any column header for a tooltip explaining what to type.
A5: 📘 WORKED EXAMPLE — How a single tech row is calculated
A6: • Wage: $25/hr • Hours/week: 40 • Billable Time: 60%
A7: • Paid hrs/mo = 40 × 4.333 weeks = 173 hours (you pay them for these)
A8: • Billable hrs/mo = 173 × 60% = 104 hours (you can invoice these)
A9: • The other 69 hours = drive time, shop time, training, slow days. You pay for them but can't bill them.
A10: • Loaded cost/mo = $25 × 173 hrs × (1 + 10% payroll tax + 12% workers comp) = $5,286
A11: • True cost per billable hour = $5,286 ÷ 104 = $50.83
A12: • If you charge a customer LESS than $50.83/hr on this tech, you LOSE money on labor alone.
A14: SHARED ASSUMPTIONS (apply to every tech)
B15: Weeks worked per month | C15: 4.333 | D15: 52 weeks ÷ 12 months = 4.333. Don't change unless you have a special schedule.
B16: Employer payroll tax % | C16: 0.1 | D16: FICA + FUTA + SUTA. Usually 8–10%. Your CPA can confirm your actual rate.
B17: Workers comp % | C17: 0.12 | D17: Restoration is high-risk — usually 8–15%. Get the exact rate from your WC policy.
B18: Default Billable Time % | C18: 0.6 | D18: Used when a tech's row is left blank. Industry typical: 55–70% for restoration.
A20: TECH ROSTER (one row per tech — add more anytime)
B21: Tech Name | C21: Wage $/hr | D21: Hrs/wk | E21: Paid hrs/mo | F21: Billable Time % | G21: Billable hrs/mo | H21: Benefits $/mo | I21: Loaded $/mo | J21: Cost / billable hr | K21: Notes
B22: Tech 1 — Lead | C22: 30 | D22: 40 | E22: =IF(B22="","",D22*$C$15) -> 173.32 | F22: 0.6 | G22: =IF(B22="","",E22*IF(F22="",$C$18,F22)) -> 103.992 | H22: 0 | I22: =IF(B22="","",(E22*C22)*(1+$C$16+$C$17)+IF(H22="",0,H22)) -> 6343.512 | J22: =IF(OR(B22="",G22=0),"",I22/G22) -> 61 | K22: Senior — higher util
B23: Tech 2 — Mid | C23: 25 | D23: 40 | E23: =IF(B23="","",D23*$C$15) -> 173.32 | F23: 0.6 | G23: =IF(B23="","",E23*IF(F23="",$C$18,F23)) -> 103.992 | H23: 0 | I23: =IF(B23="","",(E23*C23)*(1+$C$16+$C$17)+IF(H23="",0,H23)) -> 5286.26 | J23: =IF(OR(B23="",G23=0),"",I23/G23) -> 50.833333 | K23: Uses default 60%
B24: Sales - Jr | C24: 23 | D24: 25 | E24: =IF(B24="","",D24*$C$15) -> 108.325 | F24: 0.5 | G24: =IF(B24="","",E24*IF(F24="",$C$18,F24)) -> 54.1625 | H24: 0 | I24: =IF(B24="","",(E24*C24)*(1+$C$16+$C$17)+IF(H24="",0,H24)) -> 3039.5995 | J24: =IF(OR(B24="",G24=0),"",I24/G24) -> 56.12 | K24: New hire — lower util
B25: Sales - Jr | C25: 27 | D25: 40 | E25: =IF(B25="","",D25*$C$15) -> 173.32 | G25: =IF(B25="","",E25*IF(F25="",$C$18,F25)) -> 103.992 | I25: =IF(B25="","",(E25*C25)*(1+$C$16+$C$17)+IF(H25="",0,H25)) -> 5709.1608 | J25: =IF(OR(B25="",G25=0),"",I25/G25) -> 54.9
E26: =IF(B26="","",D26*$C$15) | G26: =IF(B26="","",E26*IF(F26="",$C$18,F26)) | I26: =IF(B26="","",(E26*C26)*(1+$C$16+$C$17)+IF(H26="",0,H26)) | J26: =IF(OR(B26="",G26=0),"",I26/G26)
E27: =IF(B27="","",D27*$C$15) | G27: =IF(B27="","",E27*IF(F27="",$C$18,F27)) | I27: =IF(B27="","",(E27*C27)*(1+$C$16+$C$17)+IF(H27="",0,H27)) | J27: =IF(OR(B27="",G27=0),"",I27/G27)
E28: =IF(B28="","",D28*$C$15) | G28: =IF(B28="","",E28*IF(F28="",$C$18,F28)) | I28: =IF(B28="","",(E28*C28)*(1+$C$16+$C$17)+IF(H28="",0,H28)) | J28: =IF(OR(B28="",G28=0),"",I28/G28)
E29: =IF(B29="","",D29*$C$15) | G29: =IF(B29="","",E29*IF(F29="",$C$18,F29)) | I29: =IF(B29="","",(E29*C29)*(1+$C$16+$C$17)+IF(H29="",0,H29)) | J29: =IF(OR(B29="",G29=0),"",I29/G29)
E30: =IF(B30="","",D30*$C$15) | G30: =IF(B30="","",E30*IF(F30="",$C$18,F30)) | I30: =IF(B30="","",(E30*C30)*(1+$C$16+$C$17)+IF(H30="",0,H30)) | J30: =IF(OR(B30="",G30=0),"",I30/G30)
E31: =IF(B31="","",D31*$C$15) | G31: =IF(B31="","",E31*IF(F31="",$C$18,F31)) | I31: =IF(B31="","",(E31*C31)*(1+$C$16+$C$17)+IF(H31="",0,H31)) | J31: =IF(OR(B31="",G31=0),"",I31/G31)
E32: =IF(B32="","",D32*$C$15) | G32: =IF(B32="","",E32*IF(F32="",$C$18,F32)) | I32: =IF(B32="","",(E32*C32)*(1+$C$16+$C$17)+IF(H32="",0,H32)) | J32: =IF(OR(B32="",G32=0),"",I32/G32)
E33: =IF(B33="","",D33*$C$15) | G33: =IF(B33="","",E33*IF(F33="",$C$18,F33)) | I33: =IF(B33="","",(E33*C33)*(1+$C$16+$C$17)+IF(H33="",0,H33)) | J33: =IF(OR(B33="",G33=0),"",I33/G33)
B34: ROSTER TOTALS | E34: =SUM(E22:E33) -> 628.285 | G34: =SUM(G22:G33) -> 366.1385 | H34: =SUM(H22:H33) -> 0 | I34: =SUM(I22:I33) -> 20378.532 | J34: =IFERROR(I34/G34,0) -> 55.657988
A36: TEAM SUMMARY (these numbers feed the Dashboard)
B37: Number of techs on payroll | C37: =COUNTA(B22:B33) -> 4 | D37: Counted automatically from filled-in rows above
B38: Total monthly labor cost (all techs) | C38: ='2. Labor'!$I$34 -> 20378.532 | D38: Sum of every tech's loaded cost
B39: Total billable hours available / mo | C39: ='2. Labor'!$G$34 -> 366.1385 | D39: Max hours your team CAN bill at their Billable Time %
B40: Weighted avg cost / billable hr | C40: ='2. Labor'!$J$34 -> 55.657988 | D40: 👈 Charge LESS than this on labor and you LOSE money — even before overhead.

Sheet 3. Equipment
A2: 3. Equipment Rental — per-line profitability
A3: Each row is one type of equipment you rent out. The KEY input is 'Unit-Days Rented / mo' — the total volume of rentals across all units in a typical month. Quantity Owned is only used to figure out depreciation and maintenance — the cost of having the gear on the shelf even when it isn't out on a job.
A5: 📘 WORKED EXAMPLE — How a single equipment row is calculated
A6: • You OWN 10 air movers — purchased at $200 each, useful life 60 months.
A7: • Each one costs $200 ÷ 60 = $3.33/mo to depreciate (plus $5/mo maintenance) = $8.33/mo per unit.
A8: • Total equipment cost = 10 owned × $8.33 = $83/mo (whether they're rented or sitting in the warehouse).
A9: • Last month you rented out 200 unit-days total (e.g., 10 jobs × ~5 movers × ~4 days each).
A10: • Daily rental rate: $37/day. Revenue = $37 × 200 = $7,400.
A11: • Profit = $7,400 − $83 = $7,317. That's the green column.
A12: • Fleet Utilization = 200 unit-days ÷ (10 units × 30 days) = 67%. Your fleet is working hard.
A13: • If Fleet Util shows under ~30%, you might own too much gear for the volume you're doing.
B15: Equipment Type | C15: Qty Owned | D15: Purchase $ each | E15: Useful life (mo) | F15: Daily Rental $ | G15: Unit-Days Rented / mo | H15: Maint $ / mo / unit | I15: Mo Revenue | J15: Mo Cost | K15: Mo Profit | L15: Fleet Util % | M15: Profit / Unit-Day
B16: Air mover | C16: 36 | D16: 219 | E16: 60 | F16: 37 | G16: 375 | H16: 5 | I16: =IF(C16="","",F16*G16) -> 13875 | J16: =IF(C16="","",C16*(IFERROR(D16/E16,0)+H16)) -> 311.4 | K16: =IF(C16="","",I16-J16) -> 13563.6 | L16: =IF(OR(C16="",C16=0),"",G16/(C16*30)) -> 0.34722222 | M16: =IF(OR(C16="",G16=0),"",K16/G16) -> 36.1696
B17: Dehumidifier (LGR) | C17: 7 | D17: 900 | E17: 84 | F17: 110 | G17: 105 | H17: 25 | I17: =IF(C17="","",F17*G17) -> 11550 | J17: =IF(C17="","",C17*(IFERROR(D17/E17,0)+H17)) -> 250 | K17: =IF(C17="","",I17-J17) -> 11300 | L17: =IF(OR(C17="",C17=0),"",G17/(C17*30)) -> 0.5 | M17: =IF(OR(C17="",G17=0),"",K17/G17) -> 107.61905
B18: AFD / Air scrubber | C18: 4 | D18: 450 | E18: 72 | F18: 110 | G18: 105 | H18: 20 | I18: =IF(C18="","",F18*G18) -> 11550 | J18: =IF(C18="","",C18*(IFERROR(D18/E18,0)+H18)) -> 105 | K18: =IF(C18="","",I18-J18) -> 11445 | L18: =IF(OR(C18="",C18=0),"",G18/(C18*30)) -> 0.875 | M18: =IF(OR(C18="",G18=0),"",K18/G18) -> 109
B19: Extractor | C19: 1 | D19: 3500 | E19: 84 | F19: 225 | G19: 5 | H19: 50 | I19: =IF(C19="","",F19*G19) -> 1125 | J19: =IF(C19="","",C19*(IFERROR(D19/E19,0)+H19)) -> 91.666667 | K19: =IF(C19="","",I19-J19) -> 1033.3333 | L19: =IF(OR(C19="",C19=0),"",G19/(C19*30)) -> 0.16666667 | M19: =IF(OR(C19="",G19=0),"",K19/G19) -> 206.66667
I20: =IF(C20="","",F20*G20) | J20: =IF(C20="","",C20*(IFERROR(D20/E20,0)+H20)) | K20: =IF(C20="","",I20-J20) | L20: =IF(OR(C20="",C20=0),"",G20/(C20*30)) | M20: =IF(OR(C20="",G20=0),"",K20/G20)
I21: =IF(C21="","",F21*G21) | J21: =IF(C21="","",C21*(IFERROR(D21/E21,0)+H21)) | K21: =IF(C21="","",I21-J21) | L21: =IF(OR(C21="",C21=0),"",G21/(C21*30)) | M21: =IF(OR(C21="",G21=0),"",K21/G21)
I22: =IF(C22="","",F22*G22) | J22: =IF(C22="","",C22*(IFERROR(D22/E22,0)+H22)) | K22: =IF(C22="","",I22-J22) | L22: =IF(OR(C22="",C22=0),"",G22/(C22*30)) | M22: =IF(OR(C22="",G22=0),"",K22/G22)
I23: =IF(C23="","",F23*G23) | J23: =IF(C23="","",C23*(IFERROR(D23/E23,0)+H23)) | K23: =IF(C23="","",I23-J23) | L23: =IF(OR(C23="",C23=0),"",G23/(C23*30)) | M23: =IF(OR(C23="",G23=0),"",K23/G23)
I24: =IF(C24="","",F24*G24) | J24: =IF(C24="","",C24*(IFERROR(D24/E24,0)+H24)) | K24: =IF(C24="","",I24-J24) | L24: =IF(OR(C24="",C24=0),"",G24/(C24*30)) | M24: =IF(OR(C24="",G24=0),"",K24/G24)
I25: =IF(C25="","",F25*G25) | J25: =IF(C25="","",C25*(IFERROR(D25/E25,0)+H25)) | K25: =IF(C25="","",I25-J25) | L25: =IF(OR(C25="",C25=0),"",G25/(C25*30)) | M25: =IF(OR(C25="",G25=0),"",K25/G25)
I26: =IF(C26="","",F26*G26) | J26: =IF(C26="","",C26*(IFERROR(D26/E26,0)+H26)) | K26: =IF(C26="","",I26-J26) | L26: =IF(OR(C26="",C26=0),"",G26/(C26*30)) | M26: =IF(OR(C26="",G26=0),"",K26/G26)
I27: =IF(C27="","",F27*G27) | J27: =IF(C27="","",C27*(IFERROR(D27/E27,0)+H27)) | K27: =IF(C27="","",I27-J27) | L27: =IF(OR(C27="",C27=0),"",G27/(C27*30)) | M27: =IF(OR(C27="",G27=0),"",K27/G27)
I28: =IF(C28="","",F28*G28) | J28: =IF(C28="","",C28*(IFERROR(D28/E28,0)+H28)) | K28: =IF(C28="","",I28-J28) | L28: =IF(OR(C28="",C28=0),"",G28/(C28*30)) | M28: =IF(OR(C28="",G28=0),"",K28/G28)
I29: =IF(C29="","",F29*G29) | J29: =IF(C29="","",C29*(IFERROR(D29/E29,0)+H29)) | K29: =IF(C29="","",I29-J29) | L29: =IF(OR(C29="",C29=0),"",G29/(C29*30)) | M29: =IF(OR(C29="",G29=0),"",K29/G29)
I30: =IF(C30="","",F30*G30) | J30: =IF(C30="","",C30*(IFERROR(D30/E30,0)+H30)) | K30: =IF(C30="","",I30-J30) | L30: =IF(OR(C30="",C30=0),"",G30/(C30*30)) | M30: =IF(OR(C30="",G30=0),"",K30/G30)
I31: =IF(C31="","",F31*G31) | J31: =IF(C31="","",C31*(IFERROR(D31/E31,0)+H31)) | K31: =IF(C31="","",I31-J31) | L31: =IF(OR(C31="",C31=0),"",G31/(C31*30)) | M31: =IF(OR(C31="",G31=0),"",K31/G31)
... I35: =IF(C35="","",F35*G35) | J35: =IF(C35="","",C35*(IFERROR(D35/E35,0)+H35)) | K35: =IF(C35="","",I35-J35) | L35: =IF(OR(C35="",C35=0),"",G35/(C35*30)) | M35: =IF(OR(C35="",G35=0),"",K35/G35)
B36: EQUIPMENT TOTALS | I36: =SUM(I16:I35) -> 38100 | J36: =SUM(J16:J35) -> 758.06667 | K36: =SUM(K16:K35) -> 37341.933

Sheet 4. Investments
A2: 4. Investments — vehicles, offices, big buys
A3: Each row = one investment. Use 'Cash' or 'Financed' in column C. If financed, fill in Down Payment, APR (e.g. 0.08 for 8%), and Term (months). The model figures out the monthly payment AND adds running costs (fuel, insurance, maintenance). Add as many rows as you want — each one shows up on the Dashboard and changes your break-even bill rate.
B5: Investment Name | C5: Cash or Financed? | D5: Total Cost | E5: Down Payment | F5: APR | G5: Term (mo) | H5: Useful Life (yrs) | I5: Running $ / mo | J5: Monthly Loan/Dep | K5: Total Monthly Cost | L5: Notes
B6: Service truck #1 | C6: Financed | D6: 0 | E6: 0 | F6: 0 | G6: 0 | H6: 0 | I6: 0 | J6: =IF(B6="","",IF(C6="Financed",IF(OR(G6=0,G6="",F6="",D6=""),0,PMT(F6/12,G6,-(D6-IF(E6="",0,E6)))),IF(C6="Cash",IF(OR(H6=0,H6="",D6=""),0,D6/(H6*12)),0))) -> 0 | K6: =IF(B6="","",J6+IF(I6="",0,I6)) -> 0 | L6: Loaded restoration truck
B7: Service truck #2 | C7: Cash | D7: 0 | E7: 0 | F7: 0 | G7: 0 | H7: 7 | I7: 0 | J7: =IF(B7="","",IF(C7="Financed",IF(OR(G7=0,G7="",F7="",D7=""),0,PMT(F7/12,G7,-(D7-IF(E7="",0,E7)))),IF(C7="Cash",IF(OR(H7=0,H7="",D7=""),0,D7/(H7*12)),0))) -> 0 | K7: =IF(B7="","",J7+IF(I7="",0,I7)) -> 0 | L7: Add cost to switch to financed
B8: Office space (build-out) | C8: Cash | D8: 0 | E8: 0 | F8: 0 | G8: 0 | H8: 10 | I8: 0 | J8: =IF(B8="","",IF(C8="Financed",IF(OR(G8=0,G8="",F8="",D8=""),0,PMT(F8/12,G8,-(D8-IF(E8="",0,E8)))),IF(C8="Cash",IF(OR(H8=0,H8="",D8=""),0,D8/(H8*12)),0))) -> 0 | K8: =IF(B8="","",J8+IF(I8="",0,I8)) -> 0 | L8: If you buy/build an office
J9: =IF(B9="","",IF(C9="Financed",IF(OR(G9=0,G9="",F9="",D9=""),0,PMT(F9/12,G9,-(D9-IF(E9="",0,E9)))),IF(C9="Cash",IF(OR(H9=0,H9="",D9=""),0,D9/(H9*12)),0))) | K9: =IF(B9="","",J9+IF(I9="",0,I9))
J10: =IF(B10="","",IF(C10="Financed",IF(OR(G10=0,G10="",F10="",D10=""),0,PMT(F10/12,G10,-(D10-IF(E10="",0,E10)))),IF(C10="Cash",IF(OR(H10=0,H10="",D10=""),0,D10/(H10*12)),0))) | K10: =IF(B10="","",J10+IF(I10="",0,I10))
J11: =IF(B11="","",IF(C11="Financed",IF(OR(G11=0,G11="",F11="",D11=""),0,PMT(F11/12,G11,-(D11-IF(E11="",0,E11)))),IF(C11="Cash",IF(OR(H11=0,H11="",D11=""),0,D11/(H11*12)),0))) | K11: =IF(B11="","",J11+IF(I11="",0,I11))
J12: =IF(B12="","",IF(C12="Financed",IF(OR(G12=0,G12="",F12="",D12=""),0,PMT(F12/12,G12,-(D12-IF(E12="",0,E12)))),IF(C12="Cash",IF(OR(H12=0,H12="",D12=""),0,D12/(H12*12)),0))) | K12: =IF(B12="","",J12+IF(I12="",0,I12))
J13: =IF(B13="","",IF(C13="Financed",IF(OR(G13=0,G13="",F13="",D13=""),0,PMT(F13/12,G13,-(D13-IF(E13="",0,E13)))),IF(C13="Cash",IF(OR(H13=0,H13="",D13=""),0,D13/(H13*12)),0))) | K13: =IF(B13="","",J13+IF(I13="",0,I13))
J14: =IF(B14="","",IF(C14="Financed",IF(OR(G14=0,G14="",F14="",D14=""),0,PMT(F14/12,G14,-(D14-IF(E14="",0,E14)))),IF(C14="Cash",IF(OR(H14=0,H14="",D14=""),0,D14/(H14*12)),0))) | K14: =IF(B14="","",J14+IF(I14="",0,I14))
J15: =IF(B15="","",IF(C15="Financed",IF(OR(G15=0,G15="",F15="",D15=""),0,PMT(F15/12,G15,-(D15-IF(E15="",0,E15)))),IF(C15="Cash",IF(OR(H15=0,H15="",D15=""),0,D15/(H15*12)),0))) | K15: =IF(B15="","",J15+IF(I15="",0,I15))
J16: =IF(B16="","",IF(C16="Financed",IF(OR(G16=0,G16="",F16="",D16=""),0,PMT(F16/12,G16,-(D16-IF(E16="",0,E16)))),IF(C16="Cash",IF(OR(H16=0,H16="",D16=""),0,D16/(H16*12)),0))) | K16: =IF(B16="","",J16+IF(I16="",0,I16))
J17: =IF(B17="","",IF(C17="Financed",IF(OR(G17=0,G17="",F17="",D17=""),0,PMT(F17/12,G17,-(D17-IF(E17="",0,E17)))),IF(C17="Cash",IF(OR(H17=0,H17="",D17=""),0,D17/(H17*12)),0))) | K17: =IF(B17="","",J17+IF(I17="",0,I17))
J18: =IF(B18="","",IF(C18="Financed",IF(OR(G18=0,G18="",F18="",D18=""),0,PMT(F18/12,G18,-(D18-IF(E18="",0,E18)))),IF(C18="Cash",IF(OR(H18=0,H18="",D18=""),0,D18/(H18*12)),0))) | K18: =IF(B18="","",J18+IF(I18="",0,I18))
J19: =IF(B19="","",IF(C19="Financed",IF(OR(G19=0,G19="",F19="",D19=""),0,PMT(F19/12,G19,-(D19-IF(E19="",0,E19)))),IF(C19="Cash",IF(OR(H19=0,H19="",D19=""),0,D19/(H19*12)),0))) | K19: =IF(B19="","",J19+IF(I19="",0,I19))
J20: =IF(B20="","",IF(C20="Financed",IF(OR(G20=0,G20="",F20="",D20=""),0,PMT(F20/12,G20,-(D20-IF(E20="",0,E20)))),IF(C20="Cash",IF(OR(H20=0,H20="",D20=""),0,D20/(H20*12)),0))) | K20: =IF(B20="","",J20+IF(I20="",0,I20))
... J23: =IF(B23="","",IF(C23="Financed",IF(OR(G23=0,G23="",F23="",D23=""),0,PMT(F23/12,G23,-(D23-IF(E23="",0,E23)))),IF(C23="Cash",IF(OR(H23=0,H23="",D23=""),0,D23/(H23*12)),0))) | K23: =IF(B23="","",J23+IF(I23="",0,I23))
B24: INVESTMENTS TOTAL | J24: =SUM(J6:J23) -> 0 | K24: =SUM(K6:K23) -> 0
B26: 💡 In column C type exactly 'Cash' or 'Financed' (capital letter). Default vehicle running costs ~$1,400/mo cover fuel, insurance, maintenance, registration. Adjust if your numbers differ.

Sheet 5. Packaged Items
A2: 5. Packaged Items — fixed-price kits
A3: A 'package' is a fixed-price item like a Decontamination Chamber. It bundles materials and a set number of labor hours. The model uses the team's WEIGHTED AVERAGE labor cost (from the Labor tab — accounts for all your different wages) to tell you what each package actually costs. The 'Units sold / mo' column lets you forecast revenue.
B5: Package Name | C5: Sale Price | D5: Material Cost | E5: Labor Hours | F5: Labor Cost | G5: Total Cost | H5: Profit / unit | I5: Margin % | J5: Units Sold / mo
B6: Decontamination chamber | C6: 125 | D6: 55 | E6: 2 | F6: =IF(B6="","",E6*'2. Labor'!$J$34) -> 111.31598 | G6: =IF(B6="","",D6+F6) -> 166.31598 | H6: =IF(B6="","",C6-G6) -> -41.315976 | I6: =IF(OR(B6="",C6=0),"",H6/C6) -> -0.33052781 | J6: 2
B7: Containment build-out (per room) | C7: 600 | D7: 180 | E7: 3 | F7: =IF(B7="","",E7*'2. Labor'!$J$34) -> 166.97396 | G7: =IF(B7="","",D7+F7) -> 346.97396 | H7: =IF(B7="","",C7-G7) -> 253.02604 | I7: =IF(OR(B7="",C7=0),"",H7/C7) -> 0.42171006 | J7: 2
F8: =IF(B8="","",E8*'2. Labor'!$J$34) | G8: =IF(B8="","",D8+F8) | H8: =IF(B8="","",C8-G8) | I8: =IF(OR(B8="",C8=0),"",H8/C8) | J8: 0
B9: Prep Egress | C9: 297 | D9: 25 | E9: 1 | F9: =IF(B9="","",E9*'2. Labor'!$J$34) -> 55.657988 | G9: =IF(B9="","",D9+F9) -> 80.657988 | H9: =IF(B9="","",C9-G9) -> 216.34201 | I9: =IF(OR(B9="",C9=0),"",H9/C9) -> 0.72842428 | J9: 7
B10: Large Dump | C10: 450 | D10: 100 | E10: 3 | F10: =IF(B10="","",E10*'2. Labor'!$J$34) -> 166.97396 | G10: =IF(B10="","",D10+F10) -> 266.97396 | H10: =IF(B10="","",C10-G10) -> 183.02604 | I10: =IF(OR(B10="",C10=0),"",H10/C10) -> 0.40672452 | J10: 3
B11: Small Dump | C11: 175 | D11: 50 | E11: 1.5 | F11: =IF(B11="","",E11*'2. Labor'!$J$34) -> 83.486982 | G11: =IF(B11="","",D11+F11) -> 133.48698 | H11: =IF(B11="","",C11-G11) -> 41.513018 | I11: =IF(OR(B11="",C11=0),"",H11/C11) -> 0.23721724 | J11: 3
F12: =IF(B12="","",E12*'2. Labor'!$J$34) | G12: =IF(B12="","",D12+F12) | H12: =IF(B12="","",C12-G12) | I12: =IF(OR(B12="",C12=0),"",H12/C12)
F13: =IF(B13="","",E13*'2. Labor'!$J$34) | G13: =IF(B13="","",D13+F13) | H13: =IF(B13="","",C13-G13) | I13: =IF(OR(B13="",C13=0),"",H13/C13)
F14: =IF(B14="","",E14*'2. Labor'!$J$34) | G14: =IF(B14="","",D14+F14) | H14: =IF(B14="","",C14-G14) | I14: =IF(OR(B14="",C14=0),"",H14/C14)
F15: =IF(B15="","",E15*'2. Labor'!$J$34) | G15: =IF(B15="","",D15+F15) | H15: =IF(B15="","",C15-G15) | I15: =IF(OR(B15="",C15=0),"",H15/C15)
F16: =IF(B16="","",E16*'2. Labor'!$J$34) | G16: =IF(B16="","",D16+F16) | H16: =IF(B16="","",C16-G16) | I16: =IF(OR(B16="",C16=0),"",H16/C16)
F17: =IF(B17="","",E17*'2. Labor'!$J$34) | G17: =IF(B17="","",D17+F17) | H17: =IF(B17="","",C17-G17) | I17: =IF(OR(B17="",C17=0),"",H17/C17)
F18: =IF(B18="","",E18*'2. Labor'!$J$34) | G18: =IF(B18="","",D18+F18) | H18: =IF(B18="","",C18-G18) | I18: =IF(OR(B18="",C18=0),"",H18/C18)
F19: =IF(B19="","",E19*'2. Labor'!$J$34) | G19: =IF(B19="","",D19+F19) | H19: =IF(B19="","",C19-G19) | I19: =IF(OR(B19="",C19=0),"",H19/C19)
F20: =IF(B20="","",E20*'2. Labor'!$J$34) | G20: =IF(B20="","",D20+F20) | H20: =IF(B20="","",C20-G20) | I20: =IF(OR(B20="",C20=0),"",H20/C20)
F21: =IF(B21="","",E21*'2. Labor'!$J$34) | G21: =IF(B21="","",D21+F21) | H21: =IF(B21="","",C21-G21) | I21: =IF(OR(B21="",C21=0),"",H21/C21)
F22: =IF(B22="","",E22*'2. Labor'!$J$34) | G22: =IF(B22="","",D22+F22) | H22: =IF(B22="","",C22-G22) | I22: =IF(OR(B22="",C22=0),"",H22/C22)
F23: =IF(B23="","",E23*'2. Labor'!$J$34) | G23: =IF(B23="","",D23+F23) | H23: =IF(B23="","",C23-G23) | I23: =IF(OR(B23="",C23=0),"",H23/C23)
B24: PACKAGE FORECAST TOTAL | C24: =SUMPRODUCT(C6:C23,J6:J23) -> 5404 | E24: =SUMPRODUCT(E6:E23,J6:J23) -> 30.5 | G24: =SUMPRODUCT(G6:G23,J6:J23) -> 2792.5686 | H24: =C24-G24 -> 2611.4314

Sheet 6. DASHBOARD
A2: 🎯 DASHBOARD — your answers
A3: This is the only tab that matters once your inputs are filled in. You set your forecast (billed hours and bill rate) at the top right. Everything else updates automatically. The sensitivity table at the bottom shows your profit at every reasonable rate × hours combo.
A5: YOUR MONTHLY COSTS | E5: YOUR MONTHLY FORECAST
B6: Total fixed overhead | C6: ='1. Overhead'!$C$26 -> 17776 | E6: Hours billed this month (forecast) | F6: 128
B7: Total labor (all techs) | C7: ='2. Labor'!$I$34 -> 20378.532 | E7: Avg billed rate per hour ($) | F7: 110
B8: Total equipment costs | C8: ='3. Equipment'!$J$36 -> 758.06667 | E8: Equipment revenue (forecast) | F8: ='3. Equipment'!$I$36 -> 38100
B9: Total investment costs | C9: ='4. Investments'!$K$24 -> 0 | E9: Packaged item revenue (forecast) | F9: ='5. Packaged Items'!$C$24 -> 5404
B10: TOTAL MONTHLY COSTS | C10: =SUM(C6:C9) -> 38912.599 | E10: TOTAL MONTHLY REVENUE | F10: =$F$6*$F$7+F8+F9 -> 57584
A12: 💰 THE BOTTOM LINE
B13: Monthly profit (or loss) | C13: ='6. DASHBOARD'!$F$10-'6. DASHBOARD'!$C$10 -> 18671.401 | E13: Status | F13: =IF($C$13>0,"✅ PROFITABLE",IF($C$13<0,"❌ LOSING MONEY","⚠️ BREAK-EVEN")) -> ✅ PROFITABLE
B15: Owner draw already counted? | C15: =IF('1. Overhead'!$C$26>0,"✅ Yes — included in overhead","⚠️ Check Overhead tab") -> ✅ Yes — included in overhead
A17: 📐 BREAK-EVEN — answers to your 5 questions
B18: Q1. Hours to bill at current rate to break even | C18: =MAX(0,('6. DASHBOARD'!$C$10-('3. Equipment'!$I$36+'5. Packaged Items'!$C$24))/$F$7) -> 0
B19: ↳ At current bill rate of... | C19: =$F$7 -> 110
B20: Q2. Techs needed (avg productivity per tech) | C20: =IFERROR(ROUNDUP(C18/IFERROR('2. Labor'!$G$34/'2. Labor'!$C$37,0),0),0) -> 0
B21: ↳ Your current team's max billable hours | C21: ='2. Labor'!$G$34 -> 366.1385
B22: ↳ Are you forecasting more than capacity? | C22: =IF($F$6>'2. Labor'!$G$34,"⚠️ YES — hire or work overtime","✅ Within capacity") -> ✅ Within capacity
B24: Q3. Break-even bill rate at forecasted hours | C24: =IFERROR(MAX(0,('6. DASHBOARD'!$C$10-('3. Equipment'!$I$36+'5. Packaged Items'!$C$24))/$F$6),0) -> 0
B25: ↳ At forecasted hours of... | C25: =$F$6 -> 128
B26: ↳ Charging less than this = LOSS
B28: Q4. Equipment monthly profit (all units) | C28: ='3. Equipment'!$K$36 -> 37341.933
B29: ↳ See Equipment tab for per-unit detail
B31: Q5. Investments monthly cost burden | C31: ='4. Investments'!$K$24 -> 0
B32: ↳ Hours per month needed JUST to cover investments | C32: =IFERROR('4. Investments'!$K$24/$F$7,0) -> 0
B33: ↳ Add a row on Investments tab → watch this update
B35: Reference: weighted avg cost / billable hr (labor) | C35: ='2. Labor'!$J$34 -> 55.657988
A37: 🔥 SENSITIVITY TABLE — profit at every rate × hours combo
B38: Rows = hours billed per month. Columns = your bill rate. Each cell = monthly profit (includes equipment + packages + investments + overhead + labor). Green = profit, red = loss.
B40: Hours ↓ / Rate → | C40: 65 | D40: 75 | E40: 85 | F40: 95 | G40: 105 | H40: 115 | I40: 125 | J40: 135 | K40: 150
B41: 50 | C41: =C$40*$B41+'3. Equipment'!$I$36+'5. Packaged Items'!$C$24-'6. DASHBOARD'!$C$10 -> 7841.401 | D41: =D$40*$B41+'3. Equipment'!$I$36+'5. Packaged Items'!$C$24-'6. DASHBOARD'!$C$10 -> 8341.401 | E41: =E$40*$B41+'3. Equipment'!$I$36+'5. Packaged Items'!$C$24-'6. DASHBOARD'!$C$10 -> 8841.401 | F41: =F$40*$B41+'3. Equipment'!$I$36+'5. Packaged Items'!$C$24-'6. DASHBOARD'!$C$10 -> 9341.401 | G41: =G$40*$B41+'3. Equipment'!$I$36+'5. Packaged Items'!$C$24-'6. DASHBOARD'!$C$10 -> 9841.401 | H41: =H$40*$B41+'3. Equipment'!$I$36+'5. Packaged Items'!$C$24-'6. DASHBOARD'!$C$10 -> 10341.401 | I41: =I$40*$B41+'3. Equipment'!$I$36+'5. Packaged Items'!$C$24-'6. DASHBOARD'!$C$10 -> 10841.401 | J41: =J$40*$B41+'3. Equipment'!$I$36+'5. Packaged Items'!$C$24-'6. DASHBOARD'!$C$10 -> 11341.401 | K41: =K$40*$B41+'3. Equipment'!$I$36+'5. Packaged Items'!$C$24-'6. DASHBOARD'!$C$10 -> 12091.401
B42: 100 | C42: =C$40*$B42+'3. Equipment'!$I$36+'5. Packaged Items'!$C$24-'6. DASHBOARD'!$C$10 -> 11091.401 | D42: =D$40*$B42+'3. Equipment'!$I$36+'5. Packaged Items'!$C$24-'6. DASHBOARD'!$C$10 -> 12091.401 | E42: =E$40*$B42+'3. Equipment'!$I$36+'5. Packaged Items'!$C$24-'6. DASHBOARD'!$C$10 -> 13091.401 | F42: =F$40*$B42+'3. Equipment'!$I$36+'5. Packaged Items'!$C$24-'6. DASHBOARD'!$C$10 -> 14091.401 | G42: =G$40*$B42+'3. Equipment'!$I$36+'5. Packaged Items'!$C$24-'6. DASHBOARD'!$C$10 -> 15091.401 | H42: =H$40*$B42+'3. Equipment'!$I$36+'5. Packaged Items'!$C$24-'6. DASHBOARD'!$C$10 -> 16091.401 | I42: =I$40*$B42+'3. Equipment'!$I$36+'5. Packaged Items'!$C$24-'6. DASHBOARD'!$C$10 -> 17091.401 | J42: =J$40*$B42+'3. Equipment'!$I$36+'5. Packaged Items'!$C$24-'6. DASHBOARD'!$C$10 -> 18091.401 | K42: =K$40*$B42+'3. Equipment'!$I$36+'5. Packaged Items'!$C$24-'6. DASHBOARD'!$C$10 -> 19591.401
B43: 150 | C43: =C$40*$B43+'3. Equipment'!$I$36+'5. Packaged Items'!$C$24-'6. DASHBOARD'!$C$10 -> 14341.401 | D43: =D$40*$B43+'3. Equipment'!$I$36+'5. Packaged Items'!$C$24-'6. DASHBOARD'!$C$10 -> 15841.401 | E43: =E$40*$B43+'3. Equipment'!$I$36+'5. Packaged Items'!$C$24-'6. DASHBOARD'!$C$10 -> 17341.401 | F43: =F$40*$B43+'3. Equipment'!$I$36+'5. Packaged Items'!$C$24-'6. DASHBOARD'!$C$10 -> 18841.401 | G43: =G$40*$B43+'3. Equipment'!$I$36+'5. Packaged Items'!$C$24-'6. DASHBOARD'!$C$10 -> 20341.401 | H43: =H$40*$B43+'3. Equipment'!$I$36+'5. Packaged Items'!$C$24-'6. DASHBOARD'!$C$10 -> 21841.401 | I43: =I$40*$B43+'3. Equipment'!$I$36+'5. Packaged Items'!$C$24-'6. DASHBOARD'!$C$10 -> 23341.401 | J43: =J$40*$B43+'3. Equipment'!$I$36+'5. Packaged Items'!$C$24-'6. DASHBOARD'!$C$10 -> 24841.401 | K43: =K$40*$B43+'3. Equipment'!$I$36+'5. Packaged Items'!$C$24-'6. DASHBOARD'!$C$10 -> 27091.401
B44: 200 | C44: =C$40*$B44+'3. Equipment'!$I$36+'5. Packaged Items'!$C$24-'6. DASHBOARD'!$C$10 -> 17591.401 | D44: =D$40*$B44+'3. Equipment'!$I$36+'5. Packaged Items'!$C$24-'6. DASHBOARD'!$C$10 -> 19591.401 | E44: =E$40*$B44+'3. Equipment'!$I$36+'5. Packaged Items'!$C$24-'6. DASHBOARD'!$C$10 -> 21591.401 | F44: =F$40*$B44+'3. Equipment'!$I$36+'5. Packaged Items'!$C$24-'6. DASHBOARD'!$C$10 -> 23591.401 | G44: =G$40*$B44+'3. Equipment'!$I$36+'5. Packaged Items'!$C$24-'6. DASHBOARD'!$C$10 -> 25591.401 | H44: =H$40*$B44+'3. Equipment'!$I$36+'5. Packaged Items'!$C$24-'6. DASHBOARD'!$C$10 -> 27591.401 | I44: =I$40*$B44+'3. Equipment'!$I$36+'5. Packaged Items'!$C$24-'6. DASHBOARD'!$C$10 -> 29591.401 | J44: =J$40*$B44+'3. Equipment'!$I$36+'5. Packaged Items'!$C$24-'6. DASHBOARD'!$C$10 -> 31591.401 | K44: =K$40*$B44+'3. Equipment'!$I$36+'5. Packaged Items'!$C$24-'6. DASHBOARD'!$C$10 -> 34591.401
B45: 250 | C45: =C$40*$B45+'3. Equipment'!$I$36+'5. Packaged Items'!$C$24-'6. DASHBOARD'!$C$10 -> 20841.401 | D45: =D$40*$B45+'3. Equipment'!$I$36+'5. Packaged Items'!$C$24-'6. DASHBOARD'!$C$10 -> 23341.401 | E45: =E$40*$B45+'3. Equipment'!$I$36+'5. Packaged Items'!$C$24-'6. DASHBOARD'!$C$10 -> 25841.401 | F45: =F$40*$B45+'3. Equipment'!$I$36+'5. Packaged Items'!$C$24-'6. DASHBOARD'!$C$10 -> 28341.401 | G45: =G$40*$B45+'3. Equipment'!$I$36+'5. Packaged Items'!$C$24-'6. DASHBOARD'!$C$10 -> 30841.401 | H45: =H$40*$B45+'3. Equipment'!$I$36+'5. Packaged Items'!$C$24-'6. DASHBOARD'!$C$10 -> 33341.401 | I45: =I$40*$B45+'3. Equipment'!$I$36+'5. Packaged Items'!$C$24-'6. DASHBOARD'!$C$10 -> 35841.401 | J45: =J$40*$B45+'3. Equipment'!$I$36+'5. Packaged Items'!$C$24-'6. DASHBOARD'!$C$10 -> 38341.401 | K45: =K$40*$B45+'3. Equipment'!$I$36+'5. Packaged Items'!$C$24-'6. DASHBOARD'!$C$10 -> 42091.401
B46: 300 | C46: =C$40*$B46+'3. Equipment'!$I$36+'5. Packaged Items'!$C$24-'6. DASHBOARD'!$C$10 -> 24091.401 | D46: =D$40*$B46+'3. Equipment'!$I$36+'5. Packaged Items'!$C$24-'6. DASHBOARD'!$C$10 -> 27091.401 | E46: =E$40*$B46+'3. Equipment'!$I$36+'5. Packaged Items'!$C$24-'6. DASHBOARD'!$C$10 -> 30091.401 | F46: =F$40*$B46+'3. Equipment'!$I$36+'5. Packaged Items'!$C$24-'6. DASHBOARD'!$C$10 -> 33091.401 | G46: =G$40*$B46+'3. Equipment'!$I$36+'5. Packaged Items'!$C$24-'6. DASHBOARD'!$C$10 -> 36091.401 | H46: =H$40*$B46+'3. Equipment'!$I$36+'5. Packaged Items'!$C$24-'6. DASHBOARD'!$C$10 -> 39091.401 | I46: =I$40*$B46+'3. Equipment'!$I$36+'5. Packaged Items'!$C$24-'6. DASHBOARD'!$C$10 -> 42091.401 | J46: =J$40*$B46+'3. Equipment'!$I$36+'5. Packaged Items'!$C$24-'6. DASHBOARD'!$C$10 -> 45091.401 | K46: =K$40*$B46+'3. Equipment'!$I$36+'5. Packaged Items'!$C$24-'6. DASHBOARD'!$C$10 -> 49591.401
B47: 350 | C47: =C$40*$B47+'3. Equipment'!$I$36+'5. Packaged Items'!$C$24-'6. DASHBOARD'!$C$10 -> 27341.401 | D47: =D$40*$B47+'3. Equipment'!$I$36+'5. Packaged Items'!$C$24-'6. DASHBOARD'!$C$10 -> 30841.401 | E47: =E$40*$B47+'3. Equipment'!$I$36+'5. Packaged Items'!$C$24-'6. DASHBOARD'!$C$10 -> 34341.401 | F47: =F$40*$B47+'3. Equipment'!$I$36+'5. Packaged Items'!$C$24-'6. DASHBOARD'!$C$10 -> 37841.401 | G47: =G$40*$B47+'3. Equipment'!$I$36+'5. Packaged Items'!$C$24-'6. DASHBOARD'!$C$10 -> 41341.401 | H47: =H$40*$B47+'3. Equipment'!$I$36+'5. Packaged Items'!$C$24-'6. DASHBOARD'!$C$10 -> 44841.401 | I47: =I$40*$B47+'3. Equipment'!$I$36+'5. Packaged Items'!$C$24-'6. DASHBOARD'!$C$10 -> 48341.401 | J47: =J$40*$B47+'3. Equipment'!$I$36+'5. Packaged Items'!$C$24-'6. DASHBOARD'!$C$10 -> 51841.401 | K47: =K$40*$B47+'3. Equipment'!$I$36+'5. Packaged Items'!$C$24-'6. DASHBOARD'!$C$10 -> 57091.401
B48: 400 | C48: =C$40*$B48+'3. Equipment'!$I$36+'5. Packaged Items'!$C$24-'6. DASHBOARD'!$C$10 -> 30591.401 | D48: =D$40*$B48+'3. Equipment'!$I$36+'5. Packaged Items'!$C$24-'6. DASHBOARD'!$C$10 -> 34591.401 | E48: =E$40*$B48+'3. Equipment'!$I$36+'5. Packaged Items'!$C$24-'6. DASHBOARD'!$C$10 -> 38591.401 | F48: =F$40*$B48+'3. Equipment'!$I$36+'5. Packaged Items'!$C$24-'6. DASHBOARD'!$C$10 -> 42591.401 | G48: =G$40*$B48+'3. Equipment'!$I$36+'5. Packaged Items'!$C$24-'6. DASHBOARD'!$C$10 -> 46591.401 | H48: =H$40*$B48+'3. Equipment'!$I$36+'5. Packaged Items'!$C$24-'6. DASHBOARD'!$C$10 -> 50591.401 | I48: =I$40*$B48+'3. Equipment'!$I$36+'5. Packaged Items'!$C$24-'6. DASHBOARD'!$C$10 -> 54591.401 | J48: =J$40*$B48+'3. Equipment'!$I$36+'5. Packaged Items'!$C$24-'6. DASHBOARD'!$C$10 -> 58591.401 | K48: =K$40*$B48+'3. Equipment'!$I$36+'5. Packaged Items'!$C$24-'6. DASHBOARD'!$C$10 -> 64591.401
B49: 450 | C49: =C$40*$B49+'3. Equipment'!$I$36+'5. Packaged Items'!$C$24-'6. DASHBOARD'!$C$10 -> 33841.401 | D49: =D$40*$B49+'3. Equipment'!$I$36+'5. Packaged Items'!$C$24-'6. DASHBOARD'!$C$10 -> 38341.401 | E49: =E$40*$B49+'3. Equipment'!$I$36+'5. Packaged Items'!$C$24-'6. DASHBOARD'!$C$10 -> 42841.401 | F49: =F$40*$B49+'3. Equipment'!$I$36+'5. Packaged Items'!$C$24-'6. DASHBOARD'!$C$10 -> 47341.401 | G49: =G$40*$B49+'3. Equipment'!$I$36+'5. Packaged Items'!$C$24-'6. DASHBOARD'!$C$10 -> 51841.401 | H49: =H$40*$B49+'3. Equipment'!$I$36+'5. Packaged Items'!$C$24-'6. DASHBOARD'!$C$10 -> 56341.401 | I49: =I$40*$B49+'3. Equipment'!$I$36+'5. Packaged Items'!$C$24-'6. DASHBOARD'!$C$10 -> 60841.401 | J49: =J$40*$B49+'3. Equipment'!$I$36+'5. Packaged Items'!$C$24-'6. DASHBOARD'!$C$10 -> 65341.401 | K49: =K$40*$B49+'3. Equipment'!$I$36+'5. Packaged Items'!$C$24-'6. DASHBOARD'!$C$10 -> 72091.401
B50: 500 | C50: =C$40*$B50+'3. Equipment'!$I$36+'5. Packaged Items'!$C$24-'6. DASHBOARD'!$C$10 -> 37091.401 | D50: =D$40*$B50+'3. Equipment'!$I$36+'5. Packaged Items'!$C$24-'6. DASHBOARD'!$C$10 -> 42091.401 | E50: =E$40*$B50+'3. Equipment'!$I$36+'5. Packaged Items'!$C$24-'6. DASHBOARD'!$C$10 -> 47091.401 | F50: =F$40*$B50+'3. Equipment'!$I$36+'5. Packaged Items'!$C$24-'6. DASHBOARD'!$C$10 -> 52091.401 | G50: =G$40*$B50+'3. Equipment'!$I$36+'5. Packaged Items'!$C$24-'6. DASHBOARD'!$C$10 -> 57091.401 | H50: =H$40*$B50+'3. Equipment'!$I$36+'5. Packaged Items'!$C$24-'6. DASHBOARD'!$C$10 -> 62091.401 | I50: =I$40*$B50+'3. Equipment'!$I$36+'5. Packaged Items'!$C$24-'6. DASHBOARD'!$C$10 -> 67091.401 | J50: =J$40*$B50+'3. Equipment'!$I$36+'5. Packaged Items'!$C$24-'6. DASHBOARD'!$C$10 -> 72091.401 | K50: =K$40*$B50+'3. Equipment'!$I$36+'5. Packaged Items'!$C$24-'6. DASHBOARD'!$C$10 -> 79591.401
B53: 📍 Find your real-world cell: pick the row closest to hours you actually bill, and the column closest to your average rate. That's roughly your monthly profit.
